biobb_ml/__init__.py
biobb_ml/classification/__init__.py
biobb_ml/classification/classification_predict.py
biobb_ml/classification/common.py
biobb_ml/classification/decision_tree.py
biobb_ml/classification/k_neighbors.py
biobb_ml/classification/k_neighbors_coefficient.py
biobb_ml/classification/logistic_regression.py
biobb_ml/classification/random_forest_classifier.py
biobb_ml/classification/support_vector_machine.py
biobb_ml/clustering/__init__.py
biobb_ml/clustering/agglomerative_clustering.py
biobb_ml/clustering/agglomerative_coefficient.py
biobb_ml/clustering/clustering_predict.py
biobb_ml/clustering/common.py
biobb_ml/clustering/dbscan.py
biobb_ml/clustering/k_means.py
biobb_ml/clustering/k_means_coefficient.py
biobb_ml/clustering/spectral_clustering.py
biobb_ml/clustering/spectral_coefficient.py
biobb_ml/dimensionality_reduction/__init__.py
biobb_ml/dimensionality_reduction/common.py
biobb_ml/dimensionality_reduction/pls_components.py
biobb_ml/dimensionality_reduction/pls_regression.py
biobb_ml/dimensionality_reduction/principal_component.py
biobb_ml/neural_networks/__init__.py
biobb_ml/neural_networks/autoencoder_neural_network.py
biobb_ml/neural_networks/classification_neural_network.py
biobb_ml/neural_networks/common.py
biobb_ml/neural_networks/neural_network_decode.py
biobb_ml/neural_networks/neural_network_predict.py
biobb_ml/neural_networks/recurrent_neural_network.py
biobb_ml/neural_networks/regression_neural_network.py
biobb_ml/regression/__init__.py
biobb_ml/regression/common.py
biobb_ml/regression/linear_regression.py
biobb_ml/regression/polynomial_regression.py
biobb_ml/regression/random_forest_regressor.py
biobb_ml/regression/regression_binding_predict.py
biobb_ml/regression/regression_predict.py
biobb_ml/resampling/__init__.py
biobb_ml/resampling/common.py
biobb_ml/resampling/oversampling.py
biobb_ml/resampling/reg_resampler.py
biobb_ml/resampling/resampling.py
biobb_ml/resampling/undersampling.py
biobb_ml/resampling/undersampling_binding.py
biobb_ml-4.2.0.dist-info/LICENSE
biobb_ml-4.2.0.dist-info/METADATA
biobb_ml-4.2.0.dist-info/WHEEL
biobb_ml-4.2.0.dist-info/entry_points.txt
biobb_ml-4.2.0.dist-info/top_level.txt
biobb_ml-4.2.0.dist-info/RECORD
