Metadata-Version: 2.1
Name: biobb-ml
Version: 4.2.0
Summary: Biobb_ml is the Biobb module collection to perform machine learning predictions.
Home-page: https://github.com/bioexcel/biobb_ml
Author: Biobb developers
Author-email: genis.bayarri@irbbarcelona.org
Project-URL: Documentation, http://biobb-ml.readthedocs.io/en/latest/
Project-URL: Bioexcel, https://bioexcel.eu/
Keywords: Bioinformatics Workflows BioExcel Compatibility
Classifier: Development Status :: 3 - Alpha
Classifier: Programming Language :: Python :: 3.8
Classifier: Programming Language :: Python :: 3.9
Classifier: License :: OSI Approved :: Apache Software License
Classifier: Operating System :: MacOS :: MacOS X
Classifier: Operating System :: POSIX
Requires-Python: >=3.8
License-File: LICENSE
Requires-Dist: biobb-common ==4.2.0
Requires-Dist: scikit-learn ==0.24.2
Requires-Dist: pandas >=1.3.0
Requires-Dist: seaborn ==0.10.1
Requires-Dist: tensorflow >=2.4.2
Requires-Dist: h5py ==2.10.0
Requires-Dist: imbalanced-learn ==0.7.0
